django_file_context-0.2.9.dist-info/DESCRIPTION.rst
django_file_context-0.2.9.dist-info/METADATA
django_file_context-0.2.9.dist-info/RECORD
django_file_context-0.2.9.dist-info/WHEEL
django_file_context-0.2.9.dist-info/metadata.json
django_file_context-0.2.9.dist-info/top_level.txt
file_context/__init__.py
file_context/apps.py
file_context/filters.py
file_context/managers.py
file_context/models.py
file_context/rest.py
file_context/routers.py
file_context/serializers.py
file_context/signals.py
file_context/urls.py
file_context/utils.py
file_context/viewsets.py
file_context/migrations/0001_initial.py
file_context/migrations/__init__.py
