Metadata-Version: 2.0
Name: django-file-context
Version: 0.2.9
Summary: File Context provides an easy way to store different documents/attachments
Home-page: https://gitlab.com/geoadmin-opensource/django-file-context
Author: George Silva
Author-email: georger.silva@gmail.com
License: MIT
Keywords: django-file-context
Platform: UNKNOWN
Classifier: Development Status :: 3 - Alpha
Classifier: Framework :: Django
Classifier: Framework :: Django :: 1.8
Classifier: Framework :: Django :: 1.9
Classifier: Framework :: Django :: 1.10
Classifier: Framework :: Django :: 1.11
Classifier: Framework :: Django :: 2.0
Classifier: Intended Audience :: Developers
Classifier: License :: OSI Approved :: BSD License
Classifier: Natural Language :: English
Classifier: Programming Language :: Python :: 2
Classifier: Programming Language :: Python :: 2.7
Classifier: Programming Language :: Python :: 3
Classifier: Programming Language :: Python :: 3.3
Classifier: Programming Language :: Python :: 3.4
Classifier: Programming Language :: Python :: 3.5
Classifier: Programming Language :: Python :: 3.6
Requires-Dist: django
Requires-Dist: djangorestframework
Requires-Dist: django-taggit
Requires-Dist: django-taggit-serializer
Requires-Dist: django-filter
Requires-Dist: djangorestframework-filters
Requires-Dist: django-common-models
